{
  "id": "\r\n                    10596\r\n                  ",
  "name": "Стальная бесшовная труба  EN 10220, DN 50, 60,3x2,9 mm,",
  "weight": "4,11",
  "price": "\r\n                  19,00\r\n                  ",
  "amount": "\r\n                      \r\n74.33099999999\r\n                    \r\n                    ",
  "description": "&#x43C;&#x430;&#x442;&#x435;&#x440;&#x438;&#x430;&#x43B; R-&#x441;&#x442;&#x430;&#x43B;&#x44C; 35.8 I, &#x441; &#x430;&#x442;&#x442;&#x435;&#x441;&#x442;&#x430;&#x442;&#x43E;&#x43C; &#x43F;&#x440;&#x438;&#x435;&#x43C;&#x43A;&#x438; 3.1.B <br>&#x432; &#x441;&#x43E;&#x43E;&#x442;&#x432;&#x435;&#x442;&#x441;&#x442;&#x432;&#x438;&#x438; &#x441; &#x415;&#x432;&#x440;&#x43E;&#x43F;&#x435;&#x439;&#x441;&#x43A;&#x438;&#x43C;&#x438; &#x41D;&#x43E;&#x440;&#x43C;&#x430;&#x43C;&#x438; EN 10204<br>"
}