{
  "id": "\r\n                    111157\r\n                  ",
  "name": "Sondernachlass für Austauschverfahren",
  "weight": "0,00",
  "price": "\r\n                  0,00\r\n                  ",
  "amount": "\r\n                      \r\n0\r\n                    \r\n                    ",
  "description": "###############################<br>Verbaute Ersatzteile wie z.B. Rechner, Netzteile, LCD-Displays sind<br>Austauschteile und werden von uns im Austauschverfahren bearbeitet. <br>Das ausgebaute Bauteil geht in das Eigentum von FAS &#xFC;ber.<br><br>Auch bei Austauschteilen gelten die vereinbarten Gew&#xE4;hrleistungs-<br>vereinbarungen gem. unseren derzeit g&#xFC;ltigen Lieferungs- &amp; Zahlungs-<br>bedingungen."
}