{
  "id": "111152",
  "name": "Komplettpaket für den Austausch des Zapfsäulengehäuses, ",
  "weight": "0,00",
  "price": "0,00",
  "amount": "0",
  "description": "sowie der Überprüfung und Reparatur der Zapfsäule zum Pauschalpreis.\\n\\nGilt für Zapfsäulentypen 220, 230, 240\\n\\nKomponentenausbau:\\n\\n=> Der Pauschalpreis behinhaltet den Ausbau sämtlicher Komponenten \\naus dem beschädigten Zapfsäulengehäuse.\\n\\nHydraulik- & Elektroniküberprüfung:\\n\\n=> Der Pauschalpreis behinhaltet die Überprüfung und Verwendung von \\nsonstigen benötigten Ersatzteilen für den hydraulischen & elektronischen\\nTeil der Zapfsäule.\\n\\nNeuaufbau:\\n\\n=> Der Pauschalpreis behinhaltet den kompletten Neuaufbau der Zapfsäule \\nin einem neuen Zapfsäulengehäuse.\\n\\nGewährleistung:\\n\\n=> Aufgrund des Schadensfalles sind jegliche Gewährleistungsansprüche\\nerloschen. \\n=> Sollten Sie sich noch innerhalb des Gewährleistungszeitraumes befinden,\\nerwerben Sie durch dieses Paket Ihre Standardgewährleistungszeit zxurück."
}