{
  "id": "\r\n                    11238\r\n                  ",
  "name": "ANSI-Vorschweißflansch 1\" (DN 25), Class 600, Schedule 80 S,",
  "weight": "0,00",
  "price": "\r\n                  0,00\r\n                  ",
  "amount": "\r\n                      \r\n27\r\n                    \r\n                    ",
  "description": "gem&#xE4;&#xDF; ASME B 16.5, Werkstoff ASTM A312  Grade TP316L, <br>mit 3.1 Zeugnis nach DIN EN 10204 in englischer Sprache <br>(zusammen mit Material anzuliefern) <br>ACHTUNG: Materialien aus folgenden L&#xE4;ndern <br>werden nicht akzeptiert!<br>- P.R. China<br>- Republic China on Taiwan<br>"
}