{
  "id": "167071",
  "name": "Контрольно-распределительный пункт(КРП) тип FAS - 1БР",
  "weight": "0,00",
  "price": "620,00",
  "amount": "0",
  "description": "выполнен в соответствии с чертежом \\nсостоит из:\\n- Шкаф стальной, с запорными элементами, для монтажа вне помещения с наружними размерами.......................\\n- вход/выход фланец ДУ32\\nВключает в себя следующие основные компоненты:\\n- Запорный кран на входе / на выходе\\n- Манометры на входе и выходе\\n- Регулятор давления, \\nпроизводительность до 25 кг/час \\nустановлен на мбар (до 50мбар), \\nдопустимое давление на входе до 2,5 бар.\\n\\nВес ок 22 кг\\n\\n\\nВнимание!!! Без обводной линии с запорным клапаном, без электромагнитного клапана\\n"
}