{
  "id": "18052",
  "name": "Прибор-указатель для сжиженных газов, тип FAS-W 709, PN 40,",
  "weight": "7,00",
  "price": "0,00",
  "amount": "0",
  "description": "диаметр емкости = 3000 mm, длина стержня = 610 mm стандартное\\nисполнение, соединительный фланец из материала 1.4541 (нержаве-\\nющая сталь), для стационарных, горизонтальных емкостей,\\nмонтаж горизонтальный, с 8\" шкалой, со спиральной прокладкой\\n1.4571/графит до 650°C и V2A соединительными болтами M 12 x 25, \\nс аттестатом 2.2 в соответствии с Европейскими Нормами\\n EN 10 204 "
}