{
  "id": "\r\n                    183111\r\n                  ",
  "name": "Ex-Druckmessumformer im Feldgehäuse aus Edelstahl (0-6bar)",
  "weight": "0,40",
  "price": "\r\n                  1.320,00\r\n                  ",
  "amount": "\r\n                      \r\n0\r\n                    \r\n                    ",
  "description": "Ex-Ausf&#xFC;hrung, Prozessanschluss G 1/2&quot; AG, <br>Schutzart: IP65<br>Messbereich: 0 - 6 bar, <br>Ausgangssignal: 4 - 20 mA, <br>Hilfsenergie: 24 V (DC)<br>Z&#xFC;ndschutzart: Ex II 2G Ex ia IIC T5/T6 Gb<br>Baumusterpr&#xFC;fbescheinigung / ATEX"
}