{
  "id": "\r\n                    18409\r\n                  ",
  "name": "Tankinhalt-Anzeige-System für Propan/Butan-Lagerbe-",
  "weight": "0,70",
  "price": "\r\n                  0,00\r\n                  ",
  "amount": "\r\n                      \r\n0\r\n                    \r\n                    ",
  "description": "h&#xE4;lter, drahtlose Funkdaten&#xFC;bertragung bis 1000 m,<br>komplettes Set bestehend aus:<br>am Tank:<br>- Me&#xDF;wertgeber f&#xFC;r Senior-Anzeiger<br>- Transmitter mit Befestigungssatz<br>- Batteriepack<br>im Geb&#xE4;ude:<br>- LCD-Anzeige f&#xFC;r Standardsteckdose 230 V <br>Transmitter CE gepr&#xFC;ft mit Ex-Zulassung<br>Z&#xFC;ndschutzart: II 1 G  EEx ia IIB T4<br>Bauartzulassung: Baseefa02ATEX0043 "
}