{
  "id": "20144",
  "name": "Испаритель тип FAS 3000 с водяным подогревом, ",
  "weight": "0,00",
  "price": "0,00",
  "amount": "0",
  "description": "PN 25, с изоляцией, для пропан/бутана, экспортное\\nисполнение, вход паровой фазы DN 32 PN 40, выход\\nпаровой фазы DN 65 PN 40, соединение вход/выход\\nводы фланецDN 50 PN 16, высота около 2600 mm,\\nс приемкой TЬV\\nТехнические данные:\\nрасчетное давление: 25/10 bar (газ/вода)\\nрасчетная температура 100/100° (газ/вода)\\nПроизводительность:600 kg/h \\nтемпература воды: 90/70° C \\nОписание:\\nдвойной термостат для контроля температуры газа,\\nконтроль переполнения, один электромагнтиный клапан\\nна входе, предохранительный клапан на газовой фазе,\\nместное показание газа/воды, датчик давления на\\nнагреве, электрообеспечение соответствует VDE, \\nвид защиты IP 54,напряжение 230 V, 50 Hz, испаритель\\nвEx-защитном исполнении с отдельно стоящим шкафом\\nэеклтроподключений для монтажа вне Ex-зоны, "
}