{
  "id": "201771",
  "name": "Компактнаяиспарительная установка FAS 3000",
  "weight": "0,00",
  "price": "0,00",
  "amount": "0",
  "description": "в шкафном исполнении 1000x800x300смпроизводительностью 25 кг/ч, \\nсостоящая из следующих основных компонентов:\\n\\nТеплообменник BHM 21-10 (FAS 20176)\\n-макс. рабочее давление 30 бар\\n-мин/макс. рабочая температура от -195 до +195 С°\\n-объём водяной рубашки 0,13 l \\n-Объём газовой рубашки 0,10L\\n-Температура воды на входе 70-90 С°\\n-Температура газа на выходе 55-65 С°\\n\\nУстановка оснащена:\\n\\n-2 шаровых крана (FAS 19451) на входе/выходе водяного трубопровода\\n-2 шаровых клапана (FAS 19451) на входе/выходе газового трубопровода\\n-Термоклапан на выходе из испарителя в качестве защиты испарителя в случае падения температуры воды меньше 70 C° или чрезмерного отбора паровой фазы.\\n-Предохранительный клапан (FAS 90137) cо стравливающей линии\\n-Смотровое окошко\\n-Фильтр тонкой очистки (FAS 14081) на входе газа перед испарителем\\n-Отсекатель жидкости после испарителя (14121) с сеткой, с шаровым клапаном для опорожнения, с сенсором контроля уровня (26130)\\n- Клеммная коробка (26509) EEx e II T6 с 4-мя клеммами до 4 квад. мм\\nрегуляторная группа состоит из:\\n-регулятор среднего давления (16007), макс. 80 кг/час, 1/2\" NPT\\nтип Rego 1584MH, входное давление до 25 бар, выходное давление 0,4-8,5 бар, с заводским удостоверением 2.1 в соотв. с EN10204\\nкомплектно смонтирован.\\n\\n- Шкаф электроуправления входит в поставку\\n\\n"
}