{
  "id": "\r\n                    206918\r\n                  ",
  "name": "Trockenverdampfer Typ FAS 2000, Leistung bis max 40 kg/h",
  "weight": "0,00",
  "price": "\r\n                  0,00\r\n                  ",
  "amount": "\r\n                      \r\n0\r\n                    \r\n                    ",
  "description": "Export-Version au&#xDF;erhalb EU<br>- Edelstahl Geh&#xE4;use,<br>- Geeignet f&#xFC;r den Einsatz in Ex- Zone 2<br>- 1 Magnetventil im Verdampfereingang, <br>- 1 Sicherheitsventil 25 bar im Verdampferausgang, <br>- Anschlu&#xDF;: Eingang 1/2&quot; NPT - AG / Ausgang 1/2&quot; NPT - AG<br>- Eingang und Ausgang Links,<br>- Anschlu&#xDF;fertig verkabelt, Steuerkasten am Verdampfer, <br>- Anschlu&#xDF;wert 5,8 kW, 220-240 V/50/60 Hz,<br>Hinweise:<br>- FAS Werksabnahme<br>- Mit CE und ATEX<br>Dokumentation einfach:<br>- Schaltplan<br>- Bedienungsanleitung<br>"
}