{
  "id": "\r\n                    210942\r\n                  ",
  "name": "Trockenlauf-Kolben-Kompressoraggregat, FAS - T91",
  "weight": "0,00",
  "price": "\r\n                  0,00\r\n                  ",
  "amount": "\r\n                      \r\n0\r\n                    \r\n                    ",
  "description": "ausgelegt f&#xFC;r Wasserstoff<br><br>Arbeitsvorgang:<br>Eingangsdruck 5 Barg<br>Ausgangdruck 17 Bar<br>Eingangstemperatur 20&#xB0;C<br>Ausgangstemperatur bis 130&#xB0;C<br>Durchfluss 40 nm3/h bei Geschwindigkeit 550 U/min<br><br><br>Anschl&#xFC;sse:<br>- Eingang / Ausgang  Flansch DN 20 DIN EN 1092-1 (DIN 2635)<br><br>Verrohrung und Aufbau auf einer gemeinsamen <br>Grundplatte, grundiert und lackiert.<br><br>Kompressoraggregat besteht aus folgenden Hauptkomponenten:<br>Kompressor:<br>- Typ Corken T91, einstuffige, Trockenlauf-Kolben, <br>  Sondre Ausf&#xFC;hrung: - dreifache Stopfbuchse,  Zylinder und <br>  Zylinderkopf aus ASTM A536 mit zus&#xE4;tzlicher spezieller Beschichtung <br>  O-Ringe &#x2013; Teflon, saug- und druckseitig 1 St. Manometer 0 - 25 bar<br>  max. Arbeitsdruck 23,1bar<br>- Drehstrommotor mit K&#xE4;figl&#xE4;ufer, 3,6 KW, EEx ell T3<br>230/400 V, Schutzart IP 55, Bauform B3 1415 1/min , <br>- Sicherheitsventil G 3/4&quot; mit Einstelldruck 18 bar<br>- Keilriemenantrieb mit Schutzhaube<br><br>- Ausf&#xFC;hrung nach Druckger&#xE4;terichtlinie und<br>AD 2000 Regelwerk<br>- Bedienungsanleitung<br>- EG Konformit&#xE4;tserkl&#xE4;rung<br>"
}