{
  "id": "\r\n                    21375\r\n                  ",
  "name": "Hydraulikmotor für Blackmer-Pumpe LGL 2\" E/TLGLD 2\"",
  "weight": "0,00",
  "price": "\r\n                  0,00\r\n                  ",
  "amount": "\r\n                      \r\n0\r\n                    \r\n                    ",
  "description": "Schluckvolumen 28 ccm/U<br>f&#xFC;r geschlossenen Kreislauf, mit Ausspeisung 10 bar<br>Abtriebsleistung P = 5,0 kW             Abtriebsdrehzahl n = 550 U/min<br>erf. F&#xF6;rdermenge Q = 16  l/min       erf. Betriebsdruck p = 244 bar<br>Welle   Zahnwellenprofil, Eingang/ Ausgang 3/4&quot; SAE Flansch<br>"
}