{
  "id": "217848",
  "name": "Seitenkanalpumpen-Aggregat für Ethylen FAS NZ 6-9-6,8",
  "weight": "194,00",
  "price": "0,00",
  "amount": "0",
  "description": "mit Grundplatte, Kupplung und Schutz\\ngrundiert und lackiert\\n\\nPumpe:\\nmehrstufige horizontale Kreiselpumpe in Gliedergehäusebauart\\nmit NPSH Stufe für Zulaufbetrieb, Gehäuse GGG-40.3\\n\\nEingang: DN65 / PN25/40 axial\\nAusgang: DN32 / PN25/40 vertikal aufwärts\\n\\nFördermedium : ETHYLEN\\n\\nmit einfacher Gleitringdichtung\\nMotor:\\nDrehstrom Motor \\nLeistung: 6,8 kW, 400/690V, 50Hz\\nZündschutz: EExeII T3, IP55\\nmit EU – Konformitätserklärung\\n\\nLeistung 6 m3/hbei 8,4 bar\\nmax. Differenzdruck 19 bar\\n"
}