{
  "id": "\r\n                    223960\r\n                  ",
  "name": "Anschlußblock für SV, aus Messing, 1 x W21,8 x1/14 links-AG,",
  "weight": "0,00",
  "price": "\r\n                  0,00\r\n                  ",
  "amount": "\r\n                      \r\n2\r\n                    \r\n                    ",
  "description": "1 x &#xF8;22 Schneidringverschraubung, 2 Gewindebohrungen 1/4&quot; NPT-IG <br>in Reihe und 1 Gewindebohrung um 90 Grad versetzt, jeweils senkrecht <br>zum Durchgang"
}