{
  "id": "\r\n                    22467\r\n                  ",
  "name": "Kompakt-Anlage für Flaschenbefüllung ohne Behälter",
  "weight": "0,00",
  "price": "\r\n                  0,00\r\n                  ",
  "amount": "\r\n                      \r\n0\r\n                    \r\n                    ",
  "description": "montiert auf einem Stahlrahmen (&#xDC;berdachung bauseits) und bestehend aus:<br>- Abf&#xFC;llwaage, FAS 23270, elektronische Ausf&#xFC;hrung, Typ WAEK/WAES<br>mit zwei F&#xFC;llanschl&#xFC;sse, Typ .............................................................,<br>- Handpumpe f&#xFC;r LPG, FAS 23 035, mit einem Stahlrohrgestehll <br>f&#xFC;r Flaschenentleerung,<br>- Sihi Pumpe 3108/5 mit Ex-Motor 3.6 KW, 50 Hz, 400/690 V, <br>- Rorleitungen und allen erforderlichen Armaturen: Absperrventile,<br>Schmutzf&#xE4;nger, Schaugl&#xE4;ser, Sicherheitsventile, Manometer und Manometerabsperrventile,<br>- mit Doppeldrucktaster (ohne Verkabelung) <br><br>ACHTUNG: Die 2. F&#xFC;llwaage muss separat gegen Mehrpreis bestellt werden.<br>Nicht enthalten sind folgenden Leistungen bzw. gegen Mehpreis lieferbar: <br>- ohne Elektroinstallation <br>- ohne Beleuchtung<br>- ohne Steuerung und ohne Schaltschrank<br>- ohne Luftkompressor und ohne Druckluftversorgung und Trockner<br>- ohne Container<br>- ohne Inbetriebnahme "
}