{
  "id": "22714",
  "name": "Elektronische Flüsiggas-Zapfsäule Typ 240/WD",
  "weight": "0,00",
  "price": "0,00",
  "amount": "0",
  "description": "Ausführung: Deutschland \\nWayne Dresser Gehäuse Pulverbeschichtet Typ 587 mit Wayne Dresser Elektronik, sowie farblicher Gestaltung und Beschriftung für Mineralölgesellschaft ______________\\nElektronik:\\n - elektronischer Preisrechner, WayneDresser\\n - Netzgerät 230 VAC / 50-60Hz\\n - 2 LCD-Display beleuchtet\\n - 2 Tastschalter\\nHydraulik PN25:\\n - 1 Spezialkolbenzähler für Flüssiggas mit\\neiner Durchflussleistung von 5 - 50 l/min\\n - Gasblasenabscheider mit eingebautem Feinfilter,\\nDruckhalteventil, Manometer, Rückschlagventil,\\nMembranspeicher\\n - Vollschlauchsystem\\n - 2 Hochdruckschlauch LPG19 mit Rohrbruchventil,\\nLänge 5,0m\\n - Abreißkupplung\\n - Sicherheitsventile 25 bar\\n - 2 Füllpistole Typ LG und T3 mit Feststelleinrichtung\\n - Anschluß Druckleitung:Kugelhahn1\"NPTIG\\n - Anschluß Gasrückführleitung:Kugelhahn3/4\"NPTIG\\n - eingebautes Schlauchrückholsystem\\nZertifikate:\\n - Werkszeugnis 2.1 nach EN10204\\n - amtliche Eichung gegen Mehrpreis\\n\\nDie Bauart der Zapfsäule entspricht gemäß PTB-Bauartzulassung \\nden Anforderungen der internationalen Empfehlung IR 117 \\n\"Messanlagen für Flüssigkeiten außer Wasser\" der OIML.\\n"
}