{
  "id": "230312",
  "name": "Entleerungseinheit für Flüssiggas-Flaschen, Typ E1K",
  "weight": "0,00",
  "price": "0,00",
  "amount": "0",
  "description": "mit NISPLV3, zum entleeren von LPG Flaschen,\\nStahlrahmen mit Flaschenempfänger\\nAusrüstung:\\n- Druckluftpumpe NISPLV 3 zum Absaugen von Gas und Flüssigphase\\nArbeitsdruck min. 6 bar (Luft)\\nAusgerüstet mit:\\n- 1 x mechanischer Entleerungsanschluss 1072 für W21,8x1/14, links\\n- 1 x mechanischer Entleerungsanschluss für kompakte 35 mm Jumbo Ventile\\n- 2 x LPG Schlauch mit W21,8x1 1/14 links \\n- Druckseite: Fansch DN 15, PN 40\\n- 1 x Filter\\n- 1 x Schauglass in der Druckseite\\n- Kugelhahn 1/2 NPT in der Druckseite und in der Druckluftseite\\n- 2 x Sicherheitsventil 25 bar\\n- ohne automatischer Abschaltung\\n- benötigte Druckluft ca. 400 l/min\\n"
}