{
  "id": "232582",
  "name": "Набор оборудованияNLT V1для дистанционной передачи ",
  "weight": "0,92",
  "price": "3.360,00",
  "amount": "0",
  "description": "и обработки данных о наполнении постов\\nДанные о наполнении передаются из памяти поста к ПК по радио.\\n- Принятые данные непосредственно пишутся в формате ASCII\\n- Собранные данные соответствуют точно отображению на дисплее поста\\n- Запрос по команде по кол-ву, длительности наполнения, вес газа и т.д.\\n- Обработка, архивное хранение, сортировка и конвертация данных в формат Excel*.111:111\\n*Предпосылка: Microsoft Excel на ПК устанавлен.\\n- версия на один компьютер;\\nКомпьютерные требования:\\n- операционная система: Windows 2000 или выше;\\n- свободный RS 232 или USB2.0 интерфейс;\\n- компакт-диск дисковод;\\nДальность действия радиосигнала: максимально. 100m*\\n(*дальность действия сигнала зависит от окружающего ландшафта,\\nкак здание, массивные стены, холмы и т.д.).\\nОбъем поставки:\\n- программа NLT на компакт-диске\\n- приемник с 2 съемными антеннами и блоком питания\\n- RS 232 кабель, длина примерно 2,0 м\\n- RS232 / USB2.0 адаптер с кабелем USB2.0, длиной примерно 1м\\nДрайвер к адаптеру на компакт-диске\\n\\n\\n"
}