{
  "id": "\r\n                    233105\r\n                  ",
  "name": "Verbindungsrohrleitung ca. 15 m, bestehend aus:",
  "weight": "0,00",
  "price": "\r\n                  0,00\r\n                  ",
  "amount": "\r\n                      \r\n0\r\n                    \r\n                    ",
  "description": " - Verbindungsrohrleitung DN 32 (Druckleitung und Gasr&#xFC;ckf&#xFC;hrung), <br>   PN 25, zwischen Lagerbeh&#xE4;lter und Zapfs&#xE4;uleneinheit in geschwei&#xDF;ter <br>   Ausf&#xFC;hrung mit Flanschverbindungen und den notwendigen Dichtungen,  <br>   Schrauben und Muttern<br> - Verbindungsrohrleitung &#xD8; 28 mm (Druckleitung und Entleerung), <br>   PN 25, zwischen Zapfs&#xE4;uleneinheit und Flaschenbef&#xFC;lleinrichtung <br>   in geschraubter Ausf&#xFC;hrung aus Pr&#xE4;zisionsstahlrohr und allen <br>   erforderlichen Verschraubungen<br>Hinweis:<br> - Montage bauseits<br><br>   *   *   *   Sonderausf&#xFC;hrung - Umtausch ausgeschlossen   *   *   *"
}