{
  "id": "23414",
  "name": "Электронные контрольные весы, тип WER 100ex",
  "weight": "236,00",
  "price": "0,00",
  "amount": "0",
  "description": " Взрывозащещённая установка, для полуавтоматической проверки веса\\n наполненных баллонов в зонах, опасной для взрыва (зона 1)\\n Исполнение: для цепного конвейера\\n Электронный терминал с графическим дисплеем показывает вес в \"кг\" \\n \\n Рабочая температура:от -30°C до +40°C\\n Максимальный предел взвешивания: 100 кг\\n Цена деления:50 или 100г \\n Вес тары:макс. 50 кг\\n Вес наполнения:макс. 50 кг\\n Стойка:из стали, покрыта порошковой \\nкраской\\n Платформа для баллона:400 х 500 мм\\n\\n Основание :электронное, без механически \\nдвижущихся частей,\\n Ячейка-модуль для взвешивания:OIML R 60, NTEP, точность Класс 3\\n Электропитание : \\n- встроенный блок питания 230В\\n- частота: 50-60 Гц\\n Упрвление:блок поключения со взрывозащитой\\n Заземление: кабельзаземления\\n Монтаж:Электронный терминал на стальной стойке устанавливается\\nотдельно от основы для взвешивания\\n Комплектация:\\n - пневматический стоппер баллонов с сенсором;\\n - пневматический подъёмный мост с гребнем;\\n - стойка управления с включателем;\\n - роликовый конвейер, длина 2 м, с перилами;\\n\\n-пневматический выталкиватель баллонов\\n\\n"
}