{
  "id": "\r\n                    25258\r\n                  ",
  "name": "Schlauchleitung DN 20 x 300 mm",
  "weight": "0,45",
  "price": "\r\n                  0,00\r\n                  ",
  "amount": "\r\n                      \r\n1\r\n                    \r\n                    ",
  "description": "bestehend aus:<br>Edelstahlwellschlauch Typ HR I/S DN 20<br>aus Wst. 1.4404/1.4571, parallel gewellt <br>mit einer Umflechtung aus Wst. 1.4301<br>beiderseits<br>mit Pr&#xE4;zisionsrohrenden L = 50 mm<br>gefertigt aus:<br>Rohr nahtlos AD 22 x 1,5 mm<br>aus Wst. 1.4571<br>Argon - arc verschwei&#xDF;t"
}