{
  "id": "25649",
  "name": "LPG-Füllschlauch DN 50 im Vollschlauchsystem für ",
  "weight": "0,00",
  "price": "0,00",
  "amount": "0",
  "description": "Straßentankwagen mit Sicherheitsventil und Entspannungs-\\nvorrichtung (selbstschließend mit Federkraft), Länge l = 4 m, \\nAnschlüsse: einerseits Kugelhahn DN50 PN40 mit Kupplung \\n2 1/4\" ACME mit Überwurfmutter und Stopfen aus Messing, \\nandererseits Flansch DN50 PN40 nach DIN EN 1092-1 (DIN 2635) mit Muffe ½“ zur Aufnahme eines Sicherheitsventils, komplett eingebunden, einschließlich Prüfbescheinigung\\n"
}