{
  "id": "265253",
  "name": "Elektro-Schaltkasten aus Stahlblech zur Montage",
  "weight": "0,00",
  "price": "0,00",
  "amount": "0",
  "description": "im Gebäude und außerhalb der Schutzzone,\\nzum Anschluß:\\n - An 230V Einphasenenetz\\n - 3 kW-Einphasen- Pumpenmotor mit Leistungsmessung als Trockenlaufschutz\\n - bis zu 3 Not-Aus Taster\\n - Zapfsäule zum Pumpenstart\\n - Doppeldrucktaster zum Pumpenstart\\n - Totmanntaster zum Pumpenstart - \\n - Containerbeleuchtung\\n - bis 2 Füllwaagen\\n - 1,1 kW Kompressor\\n - Doppeldrucktaster mit Kontrolleuchte für Flaschenbefüllung\\n - Signalhupe und Blitzleuchte,\\n\\nkomplett verdrahtet und auf Reihenklemmen aufgelegt"
}