{
  "id": "269539",
  "name": "Elektro-Schaltkasten aus Kunststoff zur Montage im",
  "weight": "0,00",
  "price": "2.690,00",
  "amount": "0",
  "description": "Freien oder im Gebäude und außerhalb der Ex-Schutzzone,\\nein bauseitiges Sonnen-/Wetterschutzdach wird empfohlen, \\nkomplett verdrahtet zum Anschluß von:\\n\\n - 1x Flüssiggas-Trockenverdampfer (max. 170 kg/h)\\n - 1x Magnetventil (Flüssigphase)\\n - 1x Magnetventil (Gasphase)\\n - bis zu 3 externe Not-Aus Taster\\n - optional: inkl. Einbau eines Fernübertragungsgerätes inkl. \\nAntenne (bauseitige Beistellung)\\n\\nAusgerüstet mit Hauptschalter und Doppeldrucktaster zum Ein- \\nund Ausschaltung des Verdampfers und der Gasphase.\\nEin Not-Aus Taster in der Tür.\\n\\nAbmessung: H: 600mm, B: 400mm, T: 210mm,\\nDokumentation:\\n- Klemmen- und Verdrahtungsplan\\n\\n"
}