{
  "id": "\r\n                    27527\r\n                  ",
  "name": "Betriebshandbuch für eine FG-Anlage",
  "weight": "0,00",
  "price": "\r\n                  0,00\r\n                  ",
  "amount": "\r\n                      \r\n0\r\n                    \r\n                    ",
  "description": "Grunderstellung bestehend aus:<br><br>-Genehmigungsunterlagen<br>-kompl. Anlagendokumentation<br>-Bedienungsanweisungen<br>-Notfall- und Alarmpl&#xE4;ne<br>-Werkszeugnisse<br>-Pr&#xFC;fprotokolle f&#xFC;r alle wieder-<br>  kehrenden Pr&#xFC;fungen<br>-Unterweisungsprotokollen<br><br>Nicht von uns erstellte Dokumentation ist von<br>Ihnen beizustellen.<br>"
}