{
  "id": "30503",
  "name": "Reparatur-Packung für TLGLF 3\"C",
  "weight": "5,80",
  "price": "1.525,00",
  "amount": "1",
  "description": "Teile Nr. .899225 neuer Artikel bestehend aus:\\n-1 St, O-Ring, Teile Nr.701919\\n-6 St.Treibschieber, Teile Nr.095132\\n-2 St Kugellager, Teile Nr. 903156\\n-2 St Unterlegscheibe, Teile Nr.903522\\n-2 St Dichtungen, Teile Nr. 383940\\n-1 St Schlüssel, Teile Nr.909130\\n-2 St O-Ring, Teile Nr. 702004\\n-2 St, O-Ring, Teile Nr.701919\\n-2 St Scheibe, Teile Nr.065121\\n-2 St O-Ring, Teile Nr. 711923\\n-3 St Treibstößel, part no.121607\\n-2 St Dichtungen, Teile Nr. 331918\\n-2 St Wellendichtung, Teile Nr. 334439\\n-1 St Schmutzschutzschild, Teile Nr. 701480\\n-1 St Ventil, Teile Nr. 451417\\n-1 St Feder für Ventil, Teile Nr. 451428\\n\\n"
}