{
  "id": "\r\n                    34230\r\n                  ",
  "name": "UMTS/GRPS-WLAN-Router, für TA-FAS-Typ: 420_L oder 420_L_EC",
  "weight": "0,00",
  "price": "\r\n                  0,00\r\n                  ",
  "amount": "\r\n                      \r\n0\r\n                    \r\n                    ",
  "description": "Web&apos;n Walk Box<br>*******<br>Kosten nicht im Angebot enthalten. <br>Der UMTS/GRPS-Router wird vom Kunden angeliefert!<br>Zugeh&#xF6;rig ist eine der Anlage fest zugeordnete Sim-Karte. <br>Diese darf nicht vertauscht werden!<br>*******<br>Achtung!<br>In diesem Fall kann das erforderliche Telefonmodem, f&#xFC;r die <br>Datenkommunikation der Flottenkarten, entfallen.<br><br>"
}