{
  "id": "35044",
  "name": "Autogasbetankungsanlage, Ausführung FAS/Bangladsch, ",
  "weight": "0,00",
  "price": "0,00",
  "amount": "0",
  "description": "vorbereitet zum Anschluss von einemoberirdischen \\n10 t (21 m3) Flüssiggas-Lagerbehältern und folgenden \\nArmaturen/Ausrüstungen auf einem verzinkten Grund-\\nrahmen montiert, verrohrt, grundiert und lackiert:\\n - 1 St. Kugelhähne DN 50 PN 40\\n - 1 St. Schmutzfänger DN 50 PN 40\\n - 1 St. Sicherheitsventil 25 bar\\n - 1 St. Magnetventil Ex-geschützt DN 50 PN 40, 230 V, 50 Hz\\n - 1 St. Flüssiggas-Seitenkanalpumpen-Aggregat, FAS NZ 36-8,\\nPN 25, für Zulaufbetrieb, mit einfacher Gleitringdichtung,\\nEingang Flansch DN 65, Ausgang Flansch DN 32, mit Ex-Motor \\n5 kW, 400/690 V, 50 Hz, IP 55, mit Kupplung und Kupplungsschutz\\naufgebaut auf einer gemeinsamen Grundplatte, Leistung 100 l/min \\nbeim Druck 10 bar, max. Differenzdruck 14 bar (FAS 21729)\\n - Trockenlaufschutz mittels elektrischer Leistungsmessung\\n - Manometer und Entgasungsventil in der Druckleitung\\n - 1 St. Überströmventil \\n1\"NPT-IG, mit Rückführung in die Gasphase des Beh.\\n - 1 St. Kugelhahn in der Überströmleitung, offen verplombt\\n - 1 St. Kugelhahn DN 25 PN 40 im Ausgang der Druckleitung \\n - 1 St. elektr. Zapfsäule Typ FAS-230/FAS-Q ohne Tankstellensteuerung, \\nmit 2 Coriolis-Durchflusszählern (FAS 98650), Durchflußleistung \\n5-50 L/min, mit elektr. Preisrechner FAS-Q, zwei Anzeigen, \\nNetzgerät 230 V AC/24 V DC, mit PRESET-Funktion, zwei \\nSicherheitsschalter (Tastschalter), Manometer, eingebaut in \\neinem Edelstahl-Gehäuse IP 54, mit 2 St. LPG 16 Hochdruckschlauch \\n5,0 m lang mit Abreißkupplung u. Füllpistole mit Feststelleinrichtung u. \\nAnschluß _______ (nach Kundenvorgabe), Rohrbruchventil vor dem \\nSchlauch, inkl. Schlauchrückholung\\nDokumentation:\\n - technische Dokumentation für den Behälter\\n - technische Dokumentation für das Pumpenaggregat\\n - Betriebsanweisung\\nHinweise:\\n - Die Wartungs- und Prüfvorschriften (z.B.: Dichtheitsprüfung der Pumpe)\\nsind entsprechend der Betriebsanleitung durch fachkundiges Personal"
}