{
  "id": "35386",
  "name": "Bausatz zur Umrüstung einer bestehenden Kompaktanlage",
  "weight": "0,00",
  "price": "0,00",
  "amount": "0",
  "description": "mit installierter Ebs-Ray Pumpe auf Red Jacket MID-FLOW-Pumpe, \\nbestehend aus:\\n - Druckleitungs-Anschlußsystem PN25, DN 25/DN 150, für \\nTauchmotorpumpe Typ Veeder Root und Flüssiggaslager-\\nbehälter gemäß Behälterzeichnung: ____________________,\\nkomplett verschweißt, grundiert und lackiert\\n - Flüssiggas-Tauchmotorpumpe Typ LPG Mid Flow 17-stufig\\n(FAS 21597), Leistung ca. 50 L/min bei 8,0 bar Differenz-\\ndruck (max. Differenzdruck 9,0 bar), zweiteilig, mit Ex-\\ngeschütztem Drehstrom-Motor 2,2 kW, 400 V/50 Hz, Anschluss \\nfür Druckleitungssystem 2\" NPT-IG, ohne weiteres Zubehör,\\nEx-Motor mit ATEX-Bescheinigung,\\n - inklusive Montagematerial zur Einbindung in die Überströmleitung\\nDokumentation:\\n - Schweißarbeiten ausgeführt gem. AD Regelwerk\\n - technische Dokumentation für Tauchpumpe mit Motor\\n"
}