{
  "id": "\r\n                    36184\r\n                  ",
  "name": "Treibgasbetankungsanlage mit 1 unterirdischen Behälter",
  "weight": "0,00",
  "price": "\r\n                  0,00\r\n                  ",
  "amount": "\r\n                      \r\n0\r\n                    \r\n                    ",
  "description": "4850 liter, mit getrennt aufzustellenden elektronischer Doppelzapfs&#xE4;ule<br>bestehend aus folgenden Hauptkomponenten:<br>-  Zs. Typ FAS 120-Einzel, Durchflu&#xDF;leistung  5 - 50 l/min,<br>Netzteil 230 V, 50 Hz, Drehschalter , Edelstahl-Geh&#xE4;use, <br>ein LPG 19 Hochdruckschlauch 5 m lang, mit Abrei&#xDF;kupplung <br>und Rohrbruchventil, F&#xFC;llpistoleTyp T3, Elektronik ER4<br>Kolbenz&#xE4;hler: 2 Kolben<br>- Beh&#xE4;lter 4850 liter, unterirdische Ausf&#xFC;hrung, epoxidharzbeschichtung, Durchmesser 1250 mm, <br>mit allen erdorderlichen Armaturen,<br>- Komplette Saugpumpeeinheit f&#xFC;r F&#xF6;rderung von<br>Fl&#xFC;ssiggas aus unterirdischen Beh&#xE4;ltern, bestehend aus:<br>- Fl&#xFC;ssiggas - Seitenkanalpumpen - Aggregat<br>mit NPSH - Vorstufe, Typ CEHA 3108/7  <br>Ausf&#xFC;hrung GG 25 komplett mit Drehstrommotor <br>5,0 KW 400/690 , 50Hz , EEx e II T3<br>mit Kupplung , Kupplungsschutz , Grundplatte und Aggregatmontage.<br>Eingang DN 65, Ausgang DN 32. Mit automatischer Trockenlaufcshutz&#xFC;berwachung.<br>- Eine PC-Anlage, bestehend aus Gasblasenabscheider mit<br>Manometer und Manometerabspreventil, Eingang DN 32,<br>Ausgang- Zapfs&#xE4;ule DN 32 mit Kugelhahn DN 32, PN 40 und<br>R&#xFC;ckschlagklappe DN 32, PN 40, &#xDC;berstr&#xF6;mventil 19 333-1&quot;, <br>Rohrleitung-Blende DN 25,<br>- Schmutzf&#xE4;nger DN 50 im Eingang,<br>- Schauglas DN 50 im Eingang,<br>- Anschluss f&#xFC;r evtl. Einbau von Trockenlaufschutz,<br>Anschlu&#xDF; f&#xFC;r Zapfs&#xE4;ule Flansch DN 32, Anschlu&#xDF; vom Beh&#xE4;lter Flansch DN 50, Anschlu&#xDF; -&#xDC;berstr&#xF6;mletung-Flansch DN 25,<br>- Beh&#xE4;lter, Pumpenseite ist mit Isolierflanschenpaar und Trennfunkenstrecke ausgeschtatet<br><br>Verbindung  zwischen Saugpumpeneinheit und Zapfs&#xE4;ule - bauseits."
}