{
  "id": "\r\n                    38044\r\n                  ",
  "name": "LPG Zähler 2\" NPT, mit TÜV-Bauartzulassung, ohne TVC,",
  "weight": "0,00",
  "price": "\r\n                  0,00\r\n                  ",
  "amount": "\r\n                      \r\n0\r\n                    \r\n                    ",
  "description": "Typ LC-MA7GX10, Ausf&#xFC;hrung EUROTANK, Leistung <br>75 bis 380 l/min, Durchflu&#xDF;richtung rechts nach links, <br>mit mechanischem Rollenz&#xE4;hlwerk und Bondrucker <br>Typ Kienzle 0,1 Liter, mit R&#xFC;ckschlagventil im Eingang, <br>Gasabscheider 90&#xB0; gedreht, Feinsieb und Druckhalteventil, <br>Impulsleitung mit Kugelhahn (FAS-Nr. 59946), <br>Schmutzf&#xE4;nger mit Feinsieb (FAS-Nr. 59947) montiert am<br>Impulsanschluss des Gasabscheiders, Dichtungen aus Buna, <br>Ein- und Ausgang mit Anschwei&#xDF;flanschen, <br>mit Werkszeugnis 2.3 nach EN 10 204 <br><br>Ausf&#xFC;hrung f&#xFC;r Deuschland ohne amtliche Vorpr&#xFC;fung mit<br>T&#xDC;V-Typenschild! (Vorpr&#xFC;fung gegen Mehrpreis m&#xF6;glich).<br><br><br><br>"
}