{
  "id": "384121",
  "name": "Gasblasenabscheider mit Schmutzfänger Typ FAS für Meßanlage ",
  "weight": "0,00",
  "price": "0,00",
  "amount": "0",
  "description": "bestehend aus:\\n1 St.Oberteil-Gasblasenabscheider A8340A (FAS 38.376) \\n1 St.Schmutzfänger-Gehäuseunterteil Typ FAS (FAS 383.600) OHNE SIEB\\n1 St.Flansch 2\" NPT (FAS 38.411), komplett mit 4 St. Sechs-\\nkantschrauben 3/8\"-16 UNC - 1 1/2\" (FAS 74.099) und 2 St.\\nO-Ring 07838 Buna-N 2.75 ID (FAS 38.410)\\n\\nACHTUNG! Durchflußrichtung von rechts nach links."
}