{
  "id": "454940",
  "name": "Stirnradgetriebe mit freiem Wellenende",
  "weight": "94,00",
  "price": "0,00",
  "amount": "0",
  "description": "Typ\tSK52-W\\nÜbersetzung\t7,27\\nAbtriebsdrehzahl\t193 1/min bei n1 = 1400 1/min \\nAbtriebsdrehmoment1565 Nm max. bei n1 = 1400 1/min \\nAntriebswelle\tDurchm. = 38 mm, Länge = 80 mm\\nAbtriebswelle\tDurchm. = 55 mm, Länge = 110 mm\\nBauform\tB3/M1\\nGewicht ca.\t94 kg ohne Anbauten\\nSchmierung\tMineralölfüllung ISO VG 220, ca. 2,5 Liter\\nLackierung\tLackierung 2\\nDeckanstrich\tRAL 7031 blaugrau\\nGetriebeausführung\tFußausführung (B3)\\nGetriebeoptionen\tFKM-Dichtringe (Viton)\\n\tDruckentlüftung\\n"
}