{
  "id": "\r\n                    460964\r\n                  ",
  "name": "Kreiselpumpe Typ NZ 60-7,2 STW mit NPSH Vorstufe",
  "weight": "96,00",
  "price": "\r\n                  0,00\r\n                  ",
  "amount": "\r\n                      \r\n0\r\n                    \r\n                    ",
  "description": "f&#xFC;r Fl&#xFC;ssiggas nach DIN 51622 ohne Feststoffe und Pumpenwerkstoffe nicht angreifend.<br>Nennf&#xF6;rderstrom QN = 60 m3/h (1000 Liter/min)<br>Differenzdruck = 7,2 bar<br><br>Gleitringdichtung<br>Nennf&#xF6;rderdruck pN [bar] : 7,2<br>Nennleistungsbedarf PN [kW] : 17<br>Nenndrehfrequenz nN [1/min] : ca. 2.900<br>max. zul. Druck am Druckstutzen [bar] : 30,0<br>NPSH [m] : 1,7 (bezogen auf Wasser)<br>Stufenanzahl: 5 Stufen<br><br>Anschl&#xFC;sse: <br>Saugflansch DN80, PN16 nach DIN EN 1092-2<br>Druckflansch DN65, PN 40 nach DIN EN 1092-2<br><br>********************************************************<br>Ausf&#xFC;hrung: NORMALSAUGEND, HORIZONTAL, mit Kupplungsgl&#xF6;cke zur Aufnahme von Hydraulikmotor F11-14 (PARKER)<br>********************************************************<br><br>Pumpenwerkstoffe:<br>Geh&#xE4;useteile : &apos;EN-GJS-400-18-LT<br>Laufrad : &apos;EN-GJS-500-7<br>Welle : 1.4057<br>O-Ring : FPM<br>Wellenabdichtung : GLEITRINGDICHTUNG 433.4304<br>Dichtungswerkstoffe : A/Q1/V<br><br>OHNE WEITERES ZUBEH&#xD6;R.<br><br>grundiert, lackiert<br><br>Achtung! Wichtiger Hinweis!<br>Trockenlauf der Pumpe und Betrieb gegen geschlossene Absperorgane sind unbedingt zu vermeiden. Wir empfelen Benutzung von:<br>- Trockenlaufsensor<br>- F&#xFC;llstandsw&#xE4;chter<br>- Max. Druck&#xFC;berwachung<br>- Bypassventil"
}