{
  "id": "692203",
  "name": "Flüssiggas-Lagerbehälter nach DIN 4680 ",
  "weight": "0,00",
  "price": "0,00",
  "amount": "0",
  "description": "(Haushaltsbehälter), für oberirdische Aufstellung, \\nzur Lagerung von Flüssiggas (Propan/Butan)\\nBehältergröße:\\n - 4850 L, 2,1 t\\nAnschlüsse:\\n - keine\\n- fitted with follwing equipment\\n1. Safety relief valve/s 2”, type RS 3145 + CD 45, setting pressure 17.2 bar\\n2. Filler Valve - Liquid inlet 1-1/4” NPT, tpye Rego 7579 C\\n3. Liquid withdrawal with Excess Flow Valve 1-1/4\" NPT, type Rego 3282C\\nwith ball valve 1-1/4\" NPT thread class 800, type ALFA/BONETTI\\n4. Pressure gauge with valve ¼”, type Rego 948\\n5. Liquid Level gauge, type Rochester SENIOR with 50 mm dial\\n6. Vapour withdrawal with excess flow valve 1-1/4” NPT, type Rego 3282C \\nwith ball valve 1-1/4\" NPT thread class 800, type ALFA/BONETTI\\n7. Drain 1-1/4” with excess flow valve, type Rego 3282C\\n8. Fixed ullage gauge 85%, type Rego TSS3169\\n...\\nAbnahme:\\n - Baumuster-/TÜV-Prüfung\\n - CE-Kennzeichnung nach Richtlinie 2014/68/EU über Druckgeräte,\\ninklusive Konformitätserklärung\\nBemerkungen:\\n - mit 5-jähriger Garantie auf Lackierung\\n - Zeichnung: muss durch Flamco noch erstellt werden\\n"
}