{
  "id": "69483",
  "name": "Flüssiggas-Lagerbehälter, unterirdisch, 62.000 l",
  "weight": "0,00",
  "price": "0,00",
  "amount": "0",
  "description": "- für Grabenlagerung, Erddeckung bis 1 m\\n- Durchmesser 2,5 m, Länge 13,4 m\\n- Betriebsdruck 15,6 bar, Füllung 85%\\n- Domschacht und Behälter nicht überfahrbar, \\n- Domschachtanordnung mittig\\n- Flutungsanschluss G2\"\\n- EPOXI-Isolierung\\n- Domschacht 3,0 x 1,2 x 1,1 m (L x B x H), lose zur Montage vorort\\n- Pumpenschleuse DN 150 mit Schleusenkugelhahn DN 50 mit vol-\\nlem Durchgang, Schaltwellenverlängerung und Durchführung, mit \\neiner Druckausgleichsleitung mit Rohrbruchventil, Manometer und \\nKugelhahn und einem Spül-/Entleerungsanschluss mit Sicherheits-\\nventil und Kugelhahn\\n- mit Mannloch DN 500\\n- mit allen erforderlichen Anschlüssen und Rohrdurchführ-\\nungen (ohne Armaturen)\\n- zusätzlicher Anschluss Muffe 1 1/2\"-IG für eine bauseitige Füll-\\nstandsonde\\n- mit Tragösen zum Transport des leeren Behälters\\n- Leergewicht ca. 12 t\\n- gebaut nach Druckgeräterichtlinie unter Berücksichtigung \\nder AD 2000 Merkblätter, mit CE-Kennzeichnung nach \\nDGRL und Konformitätserklärung\\n\\nnicht enthalten / bauseits:\\n- Verankerungsmaterial / Auftriebsicherung (Tiefbau)\\n- Fracht und Abladen\\n- Tiefbau, Behältergrube\\n- Beistellung Kran"
}