{
  "id": "\r\n                    83985\r\n                  ",
  "name": "Kugelhahn aus Schmiedestahl DN 100, PN 40",
  "weight": "0,00",
  "price": "\r\n                  0,00\r\n                  ",
  "amount": "\r\n                      \r\n0\r\n                    \r\n                    ",
  "description": "&quot;Lange Bauform 350 mm&quot;, Kugel und Schaltwelle<br>aus Chromstahl, voller Durchgang, Kugeldichtungen<br>aus PTFE, &quot;Fire-Safe und Antistatikschutz nach<br>BS 67 55 Part 2&quot;, Leckrate 1 DIN 3230 Teil 3<br>und Teil 5 Seite 1, mit Abnahmepr&#xFC;fzeugnis 3.1 nach<br>EN 10204 , mit Bet&#xE4;tigungshebel"
}