{
  "id": "\r\n                    89139\r\n                  ",
  "name": "Anzeiger-Großgerät Typ WCD 709-8DME, für Dimethylether,",
  "weight": "5,00",
  "price": "\r\n                  0,00\r\n                  ",
  "amount": "\r\n                      \r\n0\r\n                    \r\n                    ",
  "description": "PN 40, f&#xFC;r liegende, zylindrische Beh&#xE4;lter, <br>*** verst&#xE4;rkte Ausf&#xFC;hrung ***<br> - Einbaulage waagerecht - 37&#xB0; unterhalb der Horizontalen<br> - f&#xFC;r Stra&#xDF;entankwagen mit Federd&#xE4;mpfung<br> - Beh&#xE4;lter-Innendurchmesser 2511 mm<br> - Schaftl&#xE4;nge 1273 mm<br> - Lochbild des Anschlussflansches auf Achse<br> - mit 8&quot; Skala 3-97% nicht linear und Sonderbeschriftung DME<br> - Spiral-Dichtung 1.4571/Graphit bis 550&#xB0;C<br> - Edelstahl-Schrauben M 12 x 25 mm<br> - komplett aus Werkstoff 1.4571<br> - Greifermagnet aus Werkstoff 1.4462<br><br>Dokumentation: <br> - mit Kennzeichnung CE 2266 und Dokumentation <br>   gem&#xE4;&#xDF; DGRL 2014/68/EU (Kategorie II, Modul A1)"
}