{
  "id": "897652",
  "name": "Anzeiger-Großgerät Typ Rochester 6342C-11 für Propan/Butan, ",
  "weight": "0,00",
  "price": "0,00",
  "amount": "0",
  "description": "PN 40, für liegende, zylindrische Behälter:\\n - Einbaulage waagerecht\\n - Behälter-Innendurchmesser 3168 mm\\n - Schaftlänge .... mm\\n - Lochbild des Anschlussflansches auf Achse\\n - mit 8\" Skala\\n - Spiral-Dichtung 1.4571/Graphit bis 550°C\\n - Edelstahl-Schrauben M 12 x 25 mm\\n - Druckteil (Flansch) aus Material 1.4541 \\n - CE-Kennzeichnung nach DGRL 2014/68/EU"
}