{
  "id": "936625",
  "name": "Push-Pull Rundsteckverbinder - 5-polig - Stecker, gerade",
  "weight": "0,02",
  "price": "0,00",
  "amount": "8",
  "description": "Die Rundsteckverbinder der Serie SF12 mit Push-Pull Verriegelung sorgen für eine kompakte und sichere Verbindung. Schnelles und leichtes Stecken, Verriegeln und Trennen. Blindes und leichtes Stecken und Trennen an schwer zugänglichen Stellen durch geringen Platzbedarf. Anwendung bei Mess- und Protokollgeräten, in der Roboter- und Industrietechnik.\\n\\nSchutzart IP67 \\nLeitungs-Ø 4 - 6.5 mm\\nTemperaturbereich -25 - +85 °C\\n"
}