{
  "id": "938445",
  "name": "Поворотный привод AUMA SGEXC 05.1 с AUMA MATIC AMEXC 01.1",
  "weight": "0,00",
  "price": "0,00",
  "amount": "0",
  "description": "Версия: SG\\nВзрывозащита: 48 1ExdeIICT4 GUS №. D.03C.559\\nДиапазон поворота [°]: 80-110\\nустановить на [°]: 92\\nСоединительный фланец: F05-PLAN ISO 5211 без центрирующей кромки\\nСцепление: SGA-14 мм SW внутренний квадрат ISO5211,\\nВощеная мере. и стопорное кольцо\\nВремя работы в с / 90 °: 8\\nМаховик: 160 мм\\nРегулировка крутящего момента Z-A: 100-150 Нм регулируется\\nТемпература плавник. : N-40-40 / F15 -40C - + 40C / АЛВАНИЯ 1029\\nТекущий тип: D-1T-O140 3Ph-1Thermokette 140 ° C NC\\nНапряжение частота. V-Hz: 380-50 3-фазный переменный ток\\nМотор: SDE056-2-45K 0,06 кВт 2пол.\\nПланетарная передача: 70: 1\\nВыключатель крутящего момента: 6-K 2 входа на 1NC + 1S / Ag 250VAC / 5A\\nПереключатель пути: 8-K 2 входа на 1NC + 1S / Ag 250VAC / 5A\\nMech.Stell.-Display: 11\\nОтопление: 22,5 24 В в сочетании с AM / AC / VM\\nСхема подключения KMS: TP100 / 001\\nСтепень защиты / привода: IP67\\nЭлектрическое подключение: S-AM / AC штекер AM / SEM / AC\\nШильдик: RU-AL Русский, алюминий\\nЭкспертиза по КВ: протокол 06.03.010.03 + сертификат качества\\n\\nAMEXC 01.1\\nAUMA MATIC EXC\\nВзрывозащита: 48 1ExdeIICT4 GUS №. D.03C.559\\nРазмер для: SGEXC05.1-12.1\\nТемпература плавник. : N-40-40 -40 ° C - + 40 ° C\\nСхема подключения KMS: TP100 / 001\\nСетевое напряжение: 3X380V / 50-60HZ\\nЭлектропитание: трансформатор 49.2000P, выход потребителя: 24VDC\\nМаксимальная мощность мотора: 1,5 кВт\\nБлок питания: 50.06 реверсивные контакторы макс. 1,5 кВт\\nЗащита двигателя: 54.01 Термовыключатель\\nКонтроль: стандарт 41.00\\nУровень входного сигнала: 46,00 24 В пост. Тока, внутренний или внешний\\nпоставляется\\nВходные сигналы: 42.02 ON-STOP-CLOSE\\nВыходные сигналы: 44.03 OPEN / LOCAL REMOTE\\nЛогика управления: 48.10 Выключение: ЗАКРЫТЬ / ОТКРЫТЬ\\nSelbsthalt.:ORT-mit/FERN-mit\\nСелекторный переключатель: 51.01 LOCAL OFF REMOTE\\nУправление: 52.08 ON-STOP-CLOSE и кнопки Meldel.\\nОТКРЫТО: зеленый, СТО: красный, ЗАКРЫТО: желтый\\nОбогрев / сигнал поворота: 53,21 Обогрев: изнутри\\nМигатель: без\\nТип защиты: IP67 EN60529, в сборе к SA / SAR / SG\\nЗащита от коррозии: KS\\nЦвет: A0001 AUMA серебристо-серый\\nПокраска по LV: P1.001.01-KS 140 мкм порошковое покрытие\\nШильдик: RU-AL Русский, алюминий\\nЗнак: DE-EN-FR Немецкий-Английский-Французский\\nЭлектрическое подключение: клеммная колодка КП-105 М20х1,5 / М25х1,5 /\\nM32x1,5 с разъемом Ex\\nMontagep. Ручка часть: D\\nПринципиальная электрическая схема MSP: E310KC3 - F18E1\\nИнструкция по эксплуатации: Русский RU"
}