{
  "id": "986582",
  "name": "Счётная установка для СУГ, тип Coriolis-FAS 83E40, 2\", PN25",
  "weight": "58,00",
  "price": "17.500,00",
  "amount": "0",
  "description": "состоит из:\\n- газоотсекатель с фильтром тонкой очистки \\n- обратный клапан на входе\\n- массовый расходомерPROMASS 83E40 (FAS988615)\\n- дифференциальный клапан\\n- 3х ходомвой электромагнитный клапан\\n- вход штуцер 2\"\\n- выход штуцер 2\"\\n- производительность до 420l/min\\nЭлектронное счётное устройство состоит из:\\n- блок питания 20-55VAC / 16-62VDC\\n- цифровой дисплей\\n- протоколы HART/MOВBUS \\n- поворотный выыключатель для управления запуском насоса\\nУстановка смонтирована на общей консоли\\n\\n"
}